etrago/__init__.py
etrago/appl.py
etrago/args.json
etrago/network.py
etrago/analyze/__init__.py
etrago/analyze/calc_results.py
etrago/analyze/electrolysis_results.py
etrago/analyze/plot.py
etrago/cluster/__init__.py
etrago/cluster/electrical.py
etrago/cluster/gas.py
etrago/cluster/spatial.py
etrago/cluster/temporal.py
etrago/disaggregate/__init__.py
etrago/disaggregate/spatial.py
etrago/disaggregate/temporal.py
etrago/execute/__init__.py
etrago/execute/grid_optimization.py
etrago/execute/market_optimization.py
etrago/execute/sclopf.py
etrago/tools/__init__.py
etrago/tools/constraints.py
etrago/tools/db.py
etrago/tools/extendable.py
etrago/tools/io.py
etrago/tools/utilities.py
etrago-0.10.1.dist-info/licenses/LICENSE
etrago-0.10.1.dist-info/METADATA
etrago-0.10.1.dist-info/WHEEL
etrago-0.10.1.dist-info/top_level.txt
etrago-0.10.1.dist-info/RECORD
