Metadata-Version: 2.4
Name: eTraGo
Version: 0.10.1
Summary: electric transmission grid optimization
Home-page: https://github.com/openego/eTraGo
Author: Flensburg University of Applied Sciences, Europa-Universität Flensburg, Center for Sustainable Energy Systems Flensburg, DLR - Institute of Networked Energy Systems
Author-email: 
License: GNU Affero General Public License Version 3 (AGPL-3.0)
License-File: LICENSE
Requires-Dist: geoalchemy2>=0.3.0
Requires-Dist: geopandas
Requires-Dist: keyring
Requires-Dist: linopy==0.3.2
Requires-Dist: loguru
Requires-Dist: matplotlib<3.9,>=3.0.3
Requires-Dist: oedialect
Requires-Dist: pandas<2.2
Requires-Dist: pyomo<6.6
Requires-Dist: pypsa==0.26.2
Requires-Dist: rtree
Requires-Dist: saio
Requires-Dist: scikit-learn
Requires-Dist: setuptools>=54.2.0
Requires-Dist: shapely
Requires-Dist: sqlalchemy<1.4
Requires-Dist: tables
Requires-Dist: tilemapbase==0.4.5
Requires-Dist: tsam
Requires-Dist: xarray<2024.07.2
Provides-Extra: docs
Requires-Dist: nbsphinx; extra == "docs"
Requires-Dist: numpydoc; extra == "docs"
Requires-Dist: sphinx>=1.4; extra == "docs"
Requires-Dist: sphinx_rtd_theme; extra == "docs"
Provides-Extra: gurobipy
Requires-Dist: gurobipy; extra == "gurobipy"
Provides-Extra: cartopy
Requires-Dist: cartopy; extra == "cartopy"
Requires-Dist: requests; extra == "cartopy"
Dynamic: author
Dynamic: description
Dynamic: description-content-type
Dynamic: home-page
Dynamic: license
Dynamic: license-file
Dynamic: provides-extra
Dynamic: requires-dist
Dynamic: summary
